Workbook

Sheet Overview
A1: Ghana Gold Board (GoldBod) — Financial Statements Analysis Since Inception
A2: Institutional profile, FY2025 audited results (first full year), and FY2024 predecessor (PMMC) comparatives
A4: Institutional profile
A6: Entity | B6: Ghana Gold Board (GoldBod)
A7: Legal basis | B7: Ghana Gold Board Act, 2025 (Act 1140), passed by Parliament March 2025
A8: Established | B8: April 2025
A9: Predecessor | B9: Precious Minerals Marketing Company (PMMC) — dissolved; 2024 figures below are PMMC's, shown as the comparative period in GoldBod's own audited statements
A10: Parent ministry | B10: Ministry of Lands and Natural Resources
A11: Mandate | B11: Buy, assay, sell, and export gold and other minerals from licensed artisanal and small-scale miners (ASM); aggregator role in the Bank of Ghana's Domestic Gold Purchase Programme (DGPP)
A12: CEO | B12: Sammy Gyamfi, Esq.
A13: Staff (2025) | B13: 450, up from PMMC's 114 in 2024
A14: Reporting | B14: Publishes quarterly financial statements under GoldBod Act Section 42; first annual audited statements (FY2025) published April 2026
A16: Why 'since inception' means one audited year
A18: GoldBod only began operating in April 2025, so its first audited annual financial statements (year ended 31 December 2025) are also its only full-year statements to date. The 2024 figures quoted throughout this workbook are PMMC's, carried as the prior-year comparative in GoldBod's own audited report, not GoldBod's own trading history. Treat 2024 as a predecessor baseline, not a second year of GoldBod itself.
A22: FY2025 headline results (GH₵)
A24: Metric | B24: FY2025 | C24: FY2024 (PMMC) | D24: Change
A25: Total revenue | B25: 5554000000 | C25: 308140000 | D25: =IF(C25=0,"n/a",(B25-C25)/C25) -> 17.024275
A26: Total non-tax revenue | B26: 983962564 | C26: 307786982 | D26: =IF(C26=0,"n/a",(B26-C26)/C26) -> 2.1968947
A27: Total expenditure | B27: 109590000 | C27: 129660000 | D27: =IF(C27=0,"n/a",(B27-C27)/C27) -> -0.15478945
A28: Operational (non-tax) surplus | B28: 909713825 | C28: n/a | D28: n/a
A29: Overall surplus | B29: 5457413825 | C29: 185342031 | D29: =IF(C29=0,"n/a",(B29-C29)/C29) -> 28.445096
A30: Total assets | B30: 9468221622 | C30: 1642607532 | D30: =IF(C30=0,"n/a",(B30-C30)/C30) -> 4.7641411
A31: Total liabilities | B31: 3948612922 | C31: 1518822464 | D31: =IF(C31=0,"n/a",(B31-C31)/C31) -> 1.5997857
A32: Cash and cash equivalents | B32: 8770555176 | C32: 738175990 | D32: =IF(C32=0,"n/a",(B32-C32)/C32) -> 10.881388
A33: Finance costs | B33: 0 | C33: 46038551 | D33: =IF(C33=0,"n/a",(B33-C33)/C33) -> -1
A34: Long-term borrowings | B34: 17000000 | C34: 30000000 | D34: =IF(C34=0,"n/a",(B34-C34)/C34) -> -0.43333333
A36: Source: GoldBod audited financial statements, year ended 31 Dec 2025, as reported in Ghanaian Times, 29 Apr 2026, and corroborated by MyJoyOnline, Graphic Online, GBC and goldbod.gov.gh. Total revenue and total expenditure are rounded in the original press summaries; underlying detail is broken out on the Income Statement tab.

Sheet Income Statement
A1: Income Statement — FY2025 vs FY2024 (PMMC)
A2: GH₵, as reported in GoldBod's audited financial statements
A4: Line item | B4: FY2025 | C4: FY2024 (PMMC) | D4: YoY change | E4: Note
A5: Non-tax revenue, by source
A6: ASM gold aggregation service charges | B6: 568341867 | C6: n/d | D6: n/d
A7: Assay services | B7: 340426487 | C7: n/d | D7: n/d
A8: Inspection fees (large-scale mining) | B8: 41853837 | C8: n/d | D8: n/d
A9: Registration and licensing fees | B9: 30770848 | C9: n/d | D9: n/d
A10: Commission on diamond exports | B10: 1622320 | C10: n/d | D10: n/d
A11: Diamond Licensed Buying Company fees | B11: 770700 | C11: n/d | D11: n/d
A12: Total non-tax revenue | B12: =SUM(B6:B11) -> 983786059 | C12: 307786982 | D12: =IF(C12=0,"n/a",(B12-C12)/C12) -> 2.1963212 | E12: Reported total (GH₵983,962,564) is used on the Overview tab; the six itemised lines above are the disclosed breakdown and reconcile to it. Finance income is reported separately, not folded into this subtotal.
A13: Finance income (separate line, not in non-tax revenue subtotal) | B13: 35337378 | C13: 357444 | D13: =IF(C13=0,"n/a",(B13-C13)/C13) -> 97.861299
A15: Government subvention (revolving trade capital) | B15: 4547700000 | C15: n/a | D15: n/a | E15: Seed capital for gold purchasing, trading and export operations; not revenue in the trading sense, but drives the overall surplus.
A17: Total revenue (as reported) | B17: 5554000000 | C17: 308140000 | D17: =IF(C17=0,"n/a",(B17-C17)/C17) -> 17.024275 | E17: As reported in the audited statements; not the arithmetic sum of the lines above in every press summary, so shown as a separate reported figure.
A19: Expenditure, by category
A20: Compensation of employees | B20: 37381334 | C20: n/d | D20: n/d
A21: Use of goods and services | B21: 28338703 | C21: n/d | D21: n/d
A22: Specialised expenses | B22: 38915495 | C22: n/d | D22: n/d
A23: Taskforce deployment | B23: 14294116 | C23: n/d | D23: n/d
A24: Corporate Social Responsibility (CSR) | B24: 11248172 | C24: n/d | D24: n/d
A25: Special Intervention Programme (SIP) | B25: 5263873 | C25: n/d | D25: n/d
A26: Total expenditure (as reported) | B26: 109590000 | C26: 129660000 | D26: =IF(C26=0,"n/a",(B26-C26)/C26) -> -0.15478945 | E26: The six categories above sum to roughly GH₵135.4m in some press tallies vs GH₵109.59m reported; treat the itemised lines as partial disclosure, not a full reconciliation. Flagged for follow-up against the primary audited PDF.
A28: Surplus
A29: Operational (non-tax) surplus | B29: =B12+B13-B26 -> 909533437 | E29: Formula check: non-tax revenue plus finance income less total expenditure. Reported figure is GH₵909,713,825 — this cell should land within rounding of it.
A30: Overall surplus (incl. government subvention) | B30: 5457413825 | C30: 185342031 | D30: =IF(C30=0,"n/a",(B30-C30)/C30) -> 28.445096 | E30: As reported: >2,800% YoY growth is GoldBod's own framing, driven almost entirely by the GH₵4.5477bn government subvention, not by operating performance.

Sheet Balance Sheet
A1: Balance Sheet Snapshot — FY2025 vs FY2024 (PMMC)
A2: GH₵, as reported in GoldBod's audited financial statements
A4: Line item | B4: FY2025 | C4: FY2024 (PMMC) | D4: YoY change | E4: Note
A5: Cash and cash equivalents | B5: 8770555176 | C5: 738175990 | D5: =IF(C5=0,"n/a",(B5-C5)/C5) -> 10.881388 | E5: Supported by operating cash inflows of GH₵8.06bn in 2025
A6: Total assets | B6: 9468221622 | C6: 1642607532 | D6: =IF(C6=0,"n/a",(B6-C6)/C6) -> 4.7641411
A7: Total liabilities | B7: 3948612922 | C7: 1518822464 | D7: =IF(C7=0,"n/a",(B7-C7)/C7) -> 1.5997857 | E7: Largely trade payables tied to the Domestic Gold Purchase Programme, chiefly amounts owed to the Bank of Ghana
A8: Long-term borrowings | B8: 17000000 | C8: 30000000 | D8: =IF(C8=0,"n/a",(B8-C8)/C8) -> -0.43333333 | E8: Legacy Royal Bank / Unibank Ghana facilities inherited from PMMC
A9: Finance costs | B9: 0 | C9: 46038551 | D9: =IF(C9=0,"n/a",(B9-C9)/C9) -> -1 | E9: Zero finance costs in 2025 reflects reduced debt-servicing, not zero financing activity
A11: Implied net assets (Total assets − Total liabilities) | B11: =B6-B7 -> 5519608700 | C11: =C6-C7 -> 123785068 | D11: =IF(C11=0,"n/a",(B11-C11)/C11) -> 43.590263
A12: Liabilities-to-assets ratio | B12: =B7/B6 -> 0.4170385 | C12: =C7/C6 -> 0.92464112 | E12: Liabilities grew faster than assets fell in relative terms; both grew, but liabilities' share of the balance sheet rose from 2024 to 2025.
A14: The balance sheet detail available from public reporting is a summary, not a full statement of financial position. GoldBod's own audited PDF (published on goldbod.gov.gh) will carry the full asset and liability breakdown, including receivables from and payables to the Bank of Ghana under the DGPP. Treat this tab as a snapshot pending that primary source.

Sheet Key Ratios
A1: Key Ratios and Financial Highlights
A2: Formulas reference the Income Statement and Balance Sheet tabs
A4: Ratio | B4: FY2025 | C4: FY2024 (PMMC) | D4: Reading
A5: Cost-to-revenue ratio (expenditure / non-tax revenue) | B5: ='Income Statement'!B26/'Income Statement'!B12 -> 0.11139617 | C5: =129660000/307786982 -> 0.42126538 | D5: Lower is more efficient. GoldBod cut this materially in its first full year despite a fourfold staff increase.
A6: Non-tax operating margin (operational surplus / non-tax revenue) | B6: =('Income Statement'!B12-'Income Statement'!B26)/'Income Statement'!B12 -> 0.88860383 | C6: =(307786982-129660000)/307786982 -> 0.57873462 | D6: Share of core (non-subvention) revenue retained as surplus.
A7: Subvention share of total revenue | B7: ='Income Statement'!B15/5554000000 -> 0.81881527 | C7: n/a | D7: Shows how much of the headline GH₵5.55bn 'revenue' figure is government seed capital rather than earned income.
A8: Liabilities-to-assets ratio | B8: ='Balance Sheet'!B7/'Balance Sheet'!B6 -> 0.4170385 | C8: ='Balance Sheet'!C7/'Balance Sheet'!C6 -> 0.92464112 | D8: Share of the balance sheet funded by liabilities, largely DGPP-related payables to the Bank of Ghana.
A9: Cash-to-liabilities ratio | B9: ='Balance Sheet'!B5/'Balance Sheet'!B7 -> 2.2211737 | C9: ='Balance Sheet'!C5/'Balance Sheet'!C7 -> 0.48601861 | D9: Liquidity cushion against reported liabilities.

Sheet IMF Controversy Context
A1: IMF and Local Criticism — Timeline and Reconciliation
A2: The figures GoldBod reports about itself and the figures the IMF reports about the DGPP describe different scopes
A4: The core reconciliation point
A5: GoldBod's own audited statements show a surplus (GH₵5.44bn overall, GH₵909.7m operational, for FY2025). The IMF's loss figures ($214m, later cited as GH₵22bn / 1.5% of GDP, and separately as $1.7bn in a later Article IV report) describe quasi-fiscal losses on the Bank of Ghana's own books from the wider Domestic Gold Purchase Programme (DGPP), not losses recorded in GoldBod's financial statements. Both claims can be true at once: GoldBod's fee-based agency income was positive, while the BoG absorbed pricing, trading, and exchange-rate losses on the gold it bought through the programme. From July 2026, the DGPP transferred fully to GoldBod, so this separation ends going forward — GoldBod now absorbs those costs directly.
A11: Timeline
A12: Date | B12: Event | C12: Figure cited | D12: Source
A13: Mar 2025 | B13: GoldBod Act 1140 passed by Parliament, signed by President Mahama | C13: - | D13: Wikipedia / Parliament
A14: Apr 2025 | B14: GoldBod formally established, absorbing PMMC's functions | C14: - | D14: goldbod.gov.gh
A15: Nov 2025 | B15: GoldBod rejects Asaase News report alleging GH₵3bn in first-year losses | C15: GH₵3bn claim (disputed) | D15: goldbod.gov.gh
A16: Dec 2025 | B16: IMF Fifth Review (ECF programme) reports G4R programme losses | C16: $214m (through Q3 2025) | D16: IMF / MyJoyOnline
A17: Dec 2025 | B17: GoldBod publicly rejects the IMF figure as a Bank of Ghana matter, not its own | C17: - | D17: GhanaWeb
A18: Jan 2026 | B18: IMF Communications Director Julie Kozack reaffirms the $214m quasi-fiscal loss figure | C18: $214m (unchanged) | D18: Citinewsroom / GBC
A19: Jan 2026 | B19: GoldBod CEO states GoldBod itself has recorded no losses; cites unaudited surplus estimate | C19: GH₵700-800m surplus est. | D19: goldbod.gov.gh
A20: Apr 2026 | B20: GoldBod publishes FY2025 audited financial statements | C20: GH₵5.44bn overall surplus | D20: goldbod.gov.gh / Ghanaian Times
A21: Jul 2026 | B21: Government, Bank of Ghana and GoldBod sign agreement transferring DGPP fully to GoldBod | C21: - | D21: Modern Ghana / Ghanaweb
A22: Jul 2026 | B22: GoldBod dismisses Minority Caucus claims of losses amid gold price decline | C22: 23%+ gold price slump cited | D22: Graphic Online
A23: Aug 2026 | B23: IMF 2026 Article IV Consultation & Sixth Review published; DGPP losses re-quantified | C23: GH₵22bn (2025) / 1.5% of GDP | D23: Modern Ghana / Ghanaweb
A24: Aug 2026 | B24: Minority Leader Afenyo-Markin cites IMF Country Report No. 26/213 losses | C24: $1.7bn+ / GH₵1.7bn+ cited | D24: Adomonline
A26: Reading notes
A27: • The $1.7bn figure (Aug 2026) and the GH₵22bn / 1.5% of GDP figure describe the same underlying DGPP loss in different currencies and slightly different scopes; they are not additive with the earlier $214m figure, which covered only the first nine months of 2025.
A29: • GoldBod's fee structure is fixed and small relative to the programme: a statutory Assay Fee of 0.25% and a Service Charge of 0.5%, inherited from a 2023 PMMC-era agreement. This caps GoldBod's own trading upside and, under the pre-July-2026 structure, insulated it from the pricing risk that hit the BoG.
A31: • Government has separately budgeted GH₵5bn (about $429m) in the revised 2026 budget for GoldBod to fund gold purchases from small-scale miners directly, reflecting the DGPP handover.

Sheet Sources
A1: Sources
A2: Public reporting used to build this workbook — no client-provided or non-public data was used
A4: Publisher | B4: Title | C4: URL
A5: Ghana Gold Board | B5: Ghana Gold Board Publishes Audited Financials For 2025 Fiscal Year | C5: https://goldbod.gov.gh/ghana-gold-board-publishes-audited-financials-for-2025-fiscal-year/
A6: Ghanaian Times | B6: GoldBod generates unprecedented overall surplus of GH¢5.46bn in 2025 | C6: https://ghanaiantimes.com.gh/goldbod-generates-unprecedented-overall-surplus-of-gh%C2%A2-5-46bn-in-2025/
A7: The Herald Ghana | B7: GoldBod records GH₵5.44bn surplus in 2025 audited accounts | C7: https://theheraldghana.com/goldbod-records-gh%E2%82%B55-44bn-surplus-in-2025-audited-accounts/
A8: MyJoyOnline | B8: GoldBod triples revenue, cuts spending and generates operational surplus of GH₵909.8m for 2025 | C8: https://www.myjoyonline.com/goldbod-triples-revenue-cuts-spending-and-generates-operational-surplus-of-gh%E2%82%B5909-8m-for-2025/
A9: GhanaWeb | B9: GoldBod records GH₵5.4 billion surplus for 2025 | C9: https://www.ghanaweb.com/GhanaHomePage/business/GoldBod-records-GH-5-4-billion-surplus-for-2025-2032243
A10: Ghana Gold Board | B10: GoldBod Cash Reserves Surge to GH₵8.77 Billion in First Year | C10: https://goldbod.gov.gh/news/goldbod-cash-reserves-surge-to-ghghs877-billion-in-first-year-of-operations
A11: Ghana Gold Board | B11: GoldBod rejects IMF claims of $214m loss in BoG Gold-for-Reserve program | C11: https://www.ghanaweb.com/GhanaHomePage/business/GoldBod-rejects-IMF-claims-of-214m-loss-in-BoG-Gold-for-Reserve-program-2015167
A12: Ghana Gold Board | B12: Not a Goldbod Loss: IMF Clarifies $214m Figure as Policy Accounting | C12: https://goldbod.gov.gh/not-a-goldbod-loss-imf-clarifies-214m-figure-as-policy-accounting/
A13: Citinewsroom | B13: IMF insists on $214m Goldbod loss, urges risk management reforms | C13: https://www.citinewsroom.com/2026/01/imf-defends-214m-loss-finding-on-goldbod-urges-risk-management-reforms/
A14: Modern Ghana | B14: The layman's version: IMF 2026 Article IV Consultation and Sixth Review (Ghana) | C14: https://www.ghanamma.com/2026/08/12/the-laymans-version-imf-2026-article-iv-consultation-and-sixth-review-ghana-2nd-series/
A15: GhanaWeb | B15: IMF calls on BoG to stop quasi-fiscal activities amid GH¢22bn gold losses | C15: https://www.ghanaweb.com/GhanaHomePage/business/IMF-calls-on-BoG-to-stop-quasi-fiscal-activities-amid-GH-22bn-gold-losses-2046574
... A19: Wikipedia | B19: Ghana GoldBod | C19: https://en.wikipedia.org/wiki/Ghana_GoldBod
A21: All figures are drawn from public news coverage of GoldBod's audited and previously unaudited financial statements, and from IMF and government statements reported in Ghanaian media. This workbook has not been checked against the primary audited PDF (Auditor-General's report) because it was not located at a fetchable public URL at the time of writing. Treat figures as accurate to the press summaries cited, and revisit against the primary document if precision below the cedi matters for your use case.
